preflet/__init__.py
preflet/preflet.py
preflet-0.0.1.dist-info/METADATA
preflet-0.0.1.dist-info/WHEEL
preflet-0.0.1.dist-info/top_level.txt
preflet-0.0.1.dist-info/RECORD
