Metadata-Version: 2.1
Name: preflet
Version: 0.0.1
Summary: The official Python SDK to go along with Preflet.
Home-page: https://www.preflet.com
Author: Preflet
Author-email: preflet@outlook.com
License: MIT
Platform: UNKNOWN
Classifier: Development Status :: 4 - Beta
Classifier: License :: OSI Approved :: MIT License
Classifier: Programming Language :: Python
Classifier: Programming Language :: Python :: 3.5
Classifier: Programming Language :: Python :: 3.6
Classifier: Topic :: Software Development :: Libraries
Classifier: Topic :: Software Development :: Libraries :: Python Modules
Classifier: Intended Audience :: Developers
Requires-Python: >=3.5
Requires-Dist: requests
Requires-Dist: scikit-learn
Requires-Dist: pandas
Requires-Dist: tabulate
Requires-Dist: pycryptodome
